tf_simple_metric_learning/__init__.py
tf_simple_metric_learning/layers.py
tf_simple_metric_learning-0.1.2.dist-info/LICENSE
tf_simple_metric_learning-0.1.2.dist-info/WHEEL
tf_simple_metric_learning-0.1.2.dist-info/METADATA
tf_simple_metric_learning-0.1.2.dist-info/RECORD
