Metadata-Version: 2.1
Name: tf-simple-metric-learning
Version: 0.1.2
Summary: Metric learning layers with tf.keras
Home-page: https://github.com/daigo0927/tf-simple-metric-learning
Author: Daigo Hirooka
Author-email: daigo.hirooka@gmail.com
Requires-Python: >=3.6,<4.0
Classifier: Programming Language :: Python :: 3
Classifier: Programming Language :: Python :: 3.6
Classifier: Programming Language :: Python :: 3.7
Classifier: Programming Language :: Python :: 3.8
Requires-Dist: tensorflow (>=2.3.0,<3.0.0)
Requires-Dist: tensorflow-probability (>=0.11.0,<0.12.0)
Project-URL: Repository, https://github.com/daigo0927/tf-simple-metric-learning
